rdfloom/__init__.py
rdfloom/loom_core.py
rdfloom/loom_tabular.py
rdfloom/loomtabular.py
rdfloom-0.0.7.dist-info/METADATA
rdfloom-0.0.7.dist-info/WHEEL
rdfloom-0.0.7.dist-info/top_level.txt
rdfloom-0.0.7.dist-info/RECORD
