Metadata-Version: 2.1
Name: rdfloom
Version: 0.0.7
Summary: Python package for weaving RDF from tabular data
Home-page: UNKNOWN
Author: Andra Waagmeester
Author-email: andra@micel.io
License: MIT
Platform: UNKNOWN
Classifier: Programming Language :: Python :: 3.7
Classifier: Programming Language :: Python :: 3.8
Classifier: Programming Language :: Python :: 3.9
Classifier: Programming Language :: Python :: 3.9
Classifier: Programming Language :: Python :: 3.10
Classifier: Development Status :: 4 - Beta
Classifier: Operating System :: POSIX
Classifier: Operating System :: MacOS :: MacOS X
Classifier: Operating System :: Microsoft :: Windows
Classifier: Intended Audience :: Science/Research
Classifier: Intended Audience :: Information Technology
Classifier: Intended Audience :: Developers
Classifier: Topic :: Utilities
Classifier: Topic :: Scientific/Engineering :: Bio-Informatics
Requires-Dist: xlsxwriter
Requires-Dist: pandas
Requires-Dist: rdflib
Requires-Dist: ipywidgets
Requires-Dist: IPython
